visNETmap/__init__.py
visNETmap/visNM.py
visNETmap/base_modes/__init__.py
visNETmap/base_modes/netmap_base.py
visNETmap/base_modes/network_visual_save_base.py
visnetmap-0.1.3.3.dist-info/licenses/LICENSE
visnetmap-0.1.3.3.dist-info/METADATA
visnetmap-0.1.3.3.dist-info/WHEEL
visnetmap-0.1.3.3.dist-info/top_level.txt
visnetmap-0.1.3.3.dist-info/RECORD
