Metadata-Version: 2.4
Name: visnetmap
Version: 0.1.3.3
Summary: A short description of my package
Author-email: "Peng (Atsaniik) Yang" <peng.yang@uef.fi>
Project-URL: Homepage, https://github.com/Atsaniik/visnetmap
Project-URL: Bug Tracker, https://github.com/Atsaniik/visnetmap/issues
Classifier: Programming Language :: Python :: 3
Classifier: License :: OSI Approved :: MIT License
Classifier: Operating System :: OS Independent
Requires-Python: >=3.8
License-File: LICENSE
Requires-Dist: requests>=2.28.1
Requires-Dist: geopy
Dynamic: license-file
